mtype/__init__.py
mtype-1.4.dist-info/METADATA
mtype-1.4.dist-info/WHEEL
mtype-1.4.dist-info/licenses/LICENSE
mtype-1.4.dist-info/RECORD
