Metadata-Version: 2.1
Name: mtype
Version: 1.4
Summary: Check Type of value
Author-email: HMegaCrafter <henrisen2000@gmail.com>
License: Copyright (c) 2018 The Python Packaging Authority
Classifier: License :: OSI Approved :: MIT License
Classifier: Operating System :: OS Independent
Classifier: Programming Language :: Python :: 3
Requires-Python: >=3.7
